LICENSE
README.md
main.py
setup.cfg
setup.py
./submodules/tree-sitter-fbdl/src/parser.c
./submodules/tree-sitter-fbdl/src/scanner.c
./submodules/tree-sitter-fbdl/src/tree_sitter/parser.h
fbdl/__init__.py
fbdl/expr.py
fbdl/idgen.py
fbdl/packages.py
fbdl/pre.py
fbdl/refdict.py
fbdl/ts.py
fbdl/validation.py
fbdl.egg-info/PKG-INFO
fbdl.egg-info/SOURCES.txt
fbdl.egg-info/dependency_links.txt
fbdl.egg-info/entry_points.txt
fbdl.egg-info/top_level.txt
fbdl/inst/__init__.py
fbdl/inst/args.py
fbdl/inst/bus.py
fbdl/inst/check.py
fbdl/inst/fill.py
fbdl/inst/utils.py
fbdl/reg/__init__.py
fbdl/reg/reg.py
fbdl/tests/__init__.py
fbdl/tests/inst/__init__.py
fbdl/tests/inst/test_argument_resolution.py
fbdl/tests/packages/__init__.py
fbdl/tests/packages/test_get_ref_to_package.py
fbdl/tests/pre/__init__.py
fbdl/tests/pre/test_package_discovery.py